[
    [
        {
            "score": 0.6679,
            "prob": 0.0519
        },
        {
            "score": 0.4602,
            "prob": 0.0486
        }
    ],
    [
        {
            "score": 0.3523,
            "prob": 0.4455
        }
    ],
    [
        {
            "score": 0.2246,
            "prob": 0.2151
        },
        {
            "score": 0.1748,
            "prob": 0.0766
        }
    ],
    [
        {
            "score": 0.9956,
            "prob": 0.2279
        },
        {
            "score": 0.3234,
            "prob": 0.0474
        }
    ],
    [
        {
            "score": 0.2274,
            "prob": 0.4062
        },
        {
            "score": 0.2495,
            "prob": 0.1166
        }
    ],
    [
        {
            "score": 0.3018,
            "prob": 0.4272
        },
        {
            "score": 0.0427,
            "prob": 0.0006
        }
    ],
    [
        {
            "score": 0.9958,
            "prob": 0.2467
        },
        {
            "score": 0.2742,
            "prob": 0.0593
        }
    ],
    [
        {
            "score": 0.3154,
            "prob": 0.0699
        },
        {
            "score": 0.4918,
            "prob": 0.0597
        }
    ],
    [
        {
            "score": 0.306,
            "prob": 0.0191
        },
        {
            "score": 0.2734,
            "prob": 0.0173
        }
    ],
    [
        {
            "score": 0.5266,
            "prob": 0.4301
        },
        {
            "score": 0.4121,
            "prob": 0.0685
        }
    ],
    [
        {
            "score": 0.3268,
            "prob": 0.2369
        },
        {
            "score": 0.3659,
            "prob": 0.0191
        }
    ],
    [
        {
            "score": 0.2574,
            "prob": 0.1945
        },
        {
            "score": 0.2079,
            "prob": 0.0424
        }
    ],
    [
        {
            "score": 0.3936,
            "prob": 0.2134
        },
        {
            "score": 0.348,
            "prob": 0.0118
        }
    ],
    [
        {
            "score": 0.364,
            "prob": 0.0416
        },
        {
            "score": 0.3969,
            "prob": 0.0122
        }
    ],
    [
        {
            "score": 0.996,
            "prob": 0.3841
        },
        {
            "score": 0.3292,
            "prob": 0.2291
        }
    ],
    [
        {
            "score": 0.9945,
            "prob": 0.4749
        },
        {
            "score": 0.3425,
            "prob": 0.0092
        }
    ],
    [
        {
            "score": 0.1476,
            "prob": 0.6434
        }
    ],
    [
        {
            "score": 0.3261,
            "prob": 0.1522
        },
        {
            "score": 0.2862,
            "prob": 0.1196
        }
    ],
    [
        {
            "score": 0.2446,
            "prob": 0.2928
        },
        {
            "score": 0.3563,
            "prob": 0.0586
        }
    ],
    [
        {
            "score": 0.4086,
            "prob": 0.0062
        },
        {
            "score": 0.4084,
            "prob": 0.0052
        }
    ],
    [
        {
            "score": 0.2723,
            "prob": 0.5913
        },
        {
            "score": 0.2955,
            "prob": 0.0015
        }
    ],
    [
        {
            "score": 0.1428,
            "prob": 0.5956
        },
        {
            "score": 0.3943,
            "prob": 0.0105
        }
    ],
    [
        {
            "score": 0.1645,
            "prob": 0.2168
        },
        {
            "score": 0.1562,
            "prob": 0.06
        }
    ],
    [
        {
            "score": 0.1231,
            "prob": 0.0727
        },
        {
            "score": 0.2285,
            "prob": 0.0238
        }
    ],
    [
        {
            "score": 0.1987,
            "prob": 0.0837
        },
        {
            "score": 0.2807,
            "prob": 0.0146
        }
    ],
    [
        {
            "score": 1.0,
            "prob": 0.07
        },
        {
            "score": 0.5964,
            "prob": 0.0668
        }
    ],
    [
        {
            "score": 0.1139,
            "prob": 0.0548
        },
        {
            "score": 0.0901,
            "prob": 0.0133
        }
    ],
    [
        {
            "score": 0.3204,
            "prob": 0.095
        },
        {
            "score": 0.3646,
            "prob": 0.0565
        }
    ],
    [
        {
            "score": 0.3862,
            "prob": 0.1399
        },
        {
            "score": 0.3242,
            "prob": 0.1357
        }
    ],
    [
        {
            "score": 0.1955,
            "prob": 0.8776
        }
    ],
    [
        {
            "score": 0.9811,
            "prob": 0.0769
        },
        {
            "score": 0.2971,
            "prob": 0.0533
        }
    ],
    [
        {
            "score": 0.0814,
            "prob": 0.1741
        },
        {
            "score": 0.2796,
            "prob": 0.102
        }
    ],
    [
        {
            "score": 0.3502,
            "prob": 0.0753
        },
        {
            "score": 0.3011,
            "prob": 0.051
        }
    ],
    [
        {
            "score": 0.2961,
            "prob": 0.5261
        },
        {
            "score": 0.2238,
            "prob": 0.0042
        }
    ],
    [
        {
            "score": 0.9957,
            "prob": 0.2371
        },
        {
            "score": 0.2053,
            "prob": 0.1731
        }
    ],
    [
        {
            "score": 1.0,
            "prob": 0.865
        },
        {
            "score": 0.3808,
            "prob": 0.0099
        }
    ],
    [
        {
            "score": 0.2009,
            "prob": 0.0345
        },
        {
            "score": 0.285,
            "prob": 0.0152
        }
    ],
    [
        {
            "score": 0.3028,
            "prob": 0.404
        },
        {
            "score": 0.2896,
            "prob": 0.186
        }
    ],
    [
        {
            "score": 0.3121,
            "prob": 0.0607
        },
        {
            "score": 0.3173,
            "prob": 0.0221
        }
    ],
    [
        {
            "score": 0.3008,
            "prob": 0.2021
        },
        {
            "score": 0.2924,
            "prob": 0.1691
        }
    ],
    [
        {
            "score": 0.2113,
            "prob": 0.1961
        },
        {
            "score": 0.2042,
            "prob": 0.0805
        }
    ],
    [
        {
            "score": 0.9964,
            "prob": 0.6677
        },
        {
            "score": 0.3122,
            "prob": 0.0025
        }
    ],
    [
        {
            "score": 0.2933,
            "prob": 0.0087
        },
        {
            "score": 0.3198,
            "prob": 0.0066
        }
    ],
    [
        {
            "score": 0.261,
            "prob": 0.031
        },
        {
            "score": 0.3509,
            "prob": 0.0256
        }
    ],
    [
        {
            "score": 0.255,
            "prob": 0.8626
        },
        {
            "score": 0.1011,
            "prob": 0.0217
        }
    ],
    [
        {
            "score": 0.3688,
            "prob": 0.0989
        },
        {
            "score": 0.4177,
            "prob": 0.0551
        }
    ],
    [
        {
            "score": 0.3278,
            "prob": 0.0658
        },
        {
            "score": 0.2905,
            "prob": 0.0374
        }
    ],
    [
        {
            "score": 0.1536,
            "prob": 0.2599
        },
        {
            "score": 0.2551,
            "prob": 0.0618
        }
    ],
    [
        {
            "score": 0.2717,
            "prob": 0.0367
        },
        {
            "score": 0.361,
            "prob": 0.0083
        }
    ],
    [
        {
            "score": 0.2471,
            "prob": 0.4061
        },
        {
            "score": 0.2269,
            "prob": 0.0001
        }
    ]
]